src/__init__.py
src/actor_loader.py
actor_loader-0.1.3.dist-info/LICENSE
actor_loader-0.1.3.dist-info/METADATA
actor_loader-0.1.3.dist-info/WHEEL
actor_loader-0.1.3.dist-info/entry_points.txt
actor_loader-0.1.3.dist-info/top_level.txt
actor_loader-0.1.3.dist-info/RECORD
