Metadata-Version: 2.1
Name: actor-loader
Version: 0.1.3
Summary: Console application to load the required C-Actors into any mod.
Home-page: https://github.com/ArchLeaders/ActorLoader
Classifier: Development Status :: 3 - Alpha
Classifier: License :: OSI Approved :: GNU General Public License v3 or later (GPLv3+)
Classifier: Operating System :: OS Independent
Classifier: Programming Language :: Python :: 3 :: Only
Requires-Python: >=3.7
License-File: LICENSE
Requires-Dist: bcml (>=3.0.0)
